{
  "video_id": "8pCi4KpQ59c",
  "title": "How to Model Roof Types in AutoCAD Architecture (Step-by-Step)",
  "description": "In this step-by-step tutorial, I’ll show you how to construct four of the most commonly used and architecturally significant roof styles using AutoCAD Architecture:\n\n00:00 - Introduction\n01:10 - Dutch Hip Roof\n10:03 - Mansard Roof\n13:43 - Gambrel Roof\n18:15 - Flat Roof\n\nReady to go deeper?\nCheck out my beginner-friendly Drafting Course and AutoCAD Architecture Intermediate Courses below:\n\n👉 Are you looking to start a career in Architectural Drafting? Check this out (Get $50 off): https://coursecareers.com/a/TDVisionU?course=construction-drafting\n\n👉 AutoCAD Architecture Intermediate Level Course: https://learn.tdvisionuniversity.com/courses/3d-autocad-architecture-beginners-intermediate-course\n\n👉 Free Course (One Bedroom House): https://www.youtube.com/playlist?list=PLyLLcCaRflgCTuP493CZuUOFdMdh-a_jc\n\n👉 Download Files for One Bedroom Course: https://tdvisionuniversity.com/free-autocad-architecture-course\n\n🔶 Join this channel to get access to perks:\nhttps://www.youtube.com/channel/UC4Pjm4B8uD6XQJhvkPu6ETA/join\n\n🔶 Or join my Patreon Page:\nhttps://www.patreon.com/tdvision\n\n- - -\n\n#autocad  #architecture #onlineclasses #course \n\n- - -\n\nEMAIL\ninfo@tdvisionuniversity.com\n\nWEBSITE:\nhttps://www.TDVisionUniversity.com\n\nGEARS I USE:\nhttps://kit.co/TDVisionU\n\nFOLLOW ME ON SOCIAL MEDIA:\n@tdvision_u\nhttps://linktr.ee/tdvisionu\n\nCREDITS:\nMusic: YouTube Audio Library (free audio)",
  "uploader": "TD Vision U",
  "upload_date": "20250704",
  "duration": 1271,
  "view_count": 772,
  "like_count": 48,
  "comment_count": 8,
  "thumbnail": "https://i.ytimg.com/vi/8pCi4KpQ59c/maxresdefault.jpg",
  "url": "https://www.youtube.com/watch?v=8pCi4KpQ59c",
  "extraction_date": "2025-07-11T16:54:07.105818",
  "extractor_version": "3.0.0",
  "proxy_used": null,
  "reused_from": "storage\\AutoCAD Architecture_docs_com_audio\\How to Model Roof Types in Aut\\youtube_extracted_data\\metadata\\8pCi4KpQ59c_20250711_165402_metadata.json",
  "reused_timestamp": "2025-07-11T17:10:02.323855"
}